optipack/__init__.py
optipack/__main__.py
optipack/sdk/__init__.py
optipack/sdk/optipack_init.py
optipack/util.py
optipack-0.0.5.dist-info/LICENSE
optipack-0.0.5.dist-info/WHEEL
optipack-0.0.5.dist-info/entry_points.txt
optipack-0.0.5.dist-info/METADATA
optipack-0.0.5.dist-info/RECORD
