Metadata-Version: 2.1
Name: optipack
Version: 0.0.5
Summary: The optimal package for ML at OM
Author: indigoYoshimaru
Requires-Python: >=3.9,<4.0
Classifier: Programming Language :: Python :: 3
Classifier: Programming Language :: Python :: 3.9
Classifier: Programming Language :: Python :: 3.10
Classifier: Programming Language :: Python :: 3.11
Requires-Dist: typer (>=0.7.0,<0.8.0)
